MANIFEST.in
README.rst
setup.py
collective/__init__.py
collective.portlet.mybookmarks.egg-info/PKG-INFO
collective.portlet.mybookmarks.egg-info/SOURCES.txt
collective.portlet.mybookmarks.egg-info/dependency_links.txt
collective.portlet.mybookmarks.egg-info/entry_points.txt
collective.portlet.mybookmarks.egg-info/namespace_packages.txt
collective.portlet.mybookmarks.egg-info/not-zip-safe
collective.portlet.mybookmarks.egg-info/requires.txt
collective.portlet.mybookmarks.egg-info/top_level.txt
collective/portlet/__init__.py
collective/portlet/mybookmarks/__init__.py
collective/portlet/mybookmarks/config.py
collective/portlet/mybookmarks/configure.zcml
collective/portlet/mybookmarks/exportimport.py
collective/portlet/mybookmarks/i18n.sh
collective/portlet/mybookmarks/interfaces.py
collective/portlet/mybookmarks/permissions.zcml
collective/portlet/mybookmarks/setup.cfg
collective/portlet/mybookmarks/upgrades.py
collective/portlet/mybookmarks/upgrades.zcml
collective/portlet/mybookmarks/version.txt
collective/portlet/mybookmarks/browser/__init__.py
collective/portlet/mybookmarks/browser/configure.zcml
collective/portlet/mybookmarks/browser/my_bookmarks.py
collective/portlet/mybookmarks/browser/images/add.png
collective/portlet/mybookmarks/browser/images/delete.png
collective/portlet/mybookmarks/browser/images/lock.gif
collective/portlet/mybookmarks/browser/javascripts/bookmarks_edit.js
collective/portlet/mybookmarks/browser/javascripts/mybookmarks.js
collective/portlet/mybookmarks/browser/javascripts/mybookmarks.js.map
collective/portlet/mybookmarks/browser/javascripts/mybookmarks.min.js
collective/portlet/mybookmarks/browser/javascripts/mybookmarks.min.js.map
collective/portlet/mybookmarks/browser/stylesheets/mybookmarks.css
collective/portlet/mybookmarks/browser/stylesheets/mybookmarks.min.css
collective/portlet/mybookmarks/browser/stylesheets/mybookmarks.min.css.map
collective/portlet/mybookmarks/browser/templates/add_bookmark.pt
collective/portlet/mybookmarks/browser/templates/my_bookmarks.pt
collective/portlet/mybookmarks/browser/templates/my_bookmarks_edit.pt
collective/portlet/mybookmarks/controlpanel/__init__.py
collective/portlet/mybookmarks/controlpanel/configure.zcml
collective/portlet/mybookmarks/controlpanel/interfaces.py
collective/portlet/mybookmarks/controlpanel/view.py
collective/portlet/mybookmarks/locales/collective.portlet.mybookmarks.pot
