Metadata-Version: 1.2
Name: collective.portlet.mybookmarks
Version: 3.0.0
Summary: A portlet that allows to store some internal and external bookmarks for users
Home-page: https://github.com/RedTurtle/collective.portlet.mybookmarks
Author: RedTurtle Technology
Author-email: sviluppoplone@redturtle.it
License: GPL
Project-URL: PyPI, https://pypi.python.org/pypi/collective.portlet.mybookmarks
Project-URL: Source, https://github.com/RedTurtle/collective.portlet.mybookmarks
Project-URL: Tracker, https://github.com/RedTurtle/collective.portlet.mybookmarks/issues
Keywords: bookmark portlet user
Platform: UNKNOWN
Classifier: Framework :: Plone
Classifier: Framework :: Plone :: 5.2
Classifier: Development Status :: 5 - Production/Stable
Classifier: Programming Language :: Python
Classifier: Programming Language :: Python :: 3
Classifier: Programming Language :: Python :: 3 :: Only
Classifier: Topic :: Software Development :: Libraries :: Python Modules
Requires-Python: >=3.7
